rest_framework_condition/__init__.py
rest_framework_condition/decorators.py
tests/__init__.py
tests/conftest.py
tests/test_decorators.py
tests/urls.py
tests/views.py
django_rest_framework_condition-0.1.1.dist-info/LICENSE
django_rest_framework_condition-0.1.1.dist-info/METADATA
django_rest_framework_condition-0.1.1.dist-info/WHEEL
django_rest_framework_condition-0.1.1.dist-info/top_level.txt
django_rest_framework_condition-0.1.1.dist-info/RECORD
