Metadata-Version: 2.1
Name: django-rest-framework-condition
Version: 0.1.1
Summary: Decorators @condition, @last_modified and @etag for Django Rest Framework
Home-page: https://github.com/jozo/django-rest-framework-condition
Author: jozo
Author-email: hi@jozo.io
License: UNKNOWN
Platform: UNKNOWN
Classifier: Programming Language :: Python :: 2
Classifier: Programming Language :: Python :: 3
Classifier: Operating System :: OS Independent
Requires-Dist: Django
